janch/__init__.py
janch/cli.py
janch/api/__init__.py
janch/api/info.py
janch/api/main.py
janch/components/__init__.py
janch/components/formatters.py
janch/components/gatherers.py
janch/components/inspectors.py
janch/components/loggers.py
janch/utils/__init__.py
janch/utils/constants.py
janch/utils/context.py
janch/utils/display.py
janch/utils/engine.py
janch-0.0.2.dist-info/LICENSE
janch-0.0.2.dist-info/METADATA
janch-0.0.2.dist-info/WHEEL
janch-0.0.2.dist-info/entry_points.txt
janch-0.0.2.dist-info/top_level.txt
janch-0.0.2.dist-info/RECORD
