Metadata-Version: 2.1
Name: janch
Version: 0.0.2
Summary: A YAML config centric tool to act on your service status
Home-page: https://github.com/janch-tech/janch
Author: taarimalta
Author-email: 
License: UNKNOWN
Platform: UNKNOWN
Classifier: Programming Language :: Python :: 3
Classifier: License :: OSI Approved :: MIT License
Classifier: Operating System :: OS Independent
Requires-Python: >=3.8
Requires-Dist: PyYAML (>=5.3.1)
Requires-Dist: aiohttp (>=3.7.0)
Requires-Dist: click (>=7.1.2)
Requires-Dist: python-dotenv (>=0.14.0)
